cadenza_sdk/__init__.py
cadenza_sdk/_base_client.py
cadenza_sdk/_client.py
cadenza_sdk/_compat.py
cadenza_sdk/_constants.py
cadenza_sdk/_exceptions.py
cadenza_sdk/_files.py
cadenza_sdk/_models.py
cadenza_sdk/_qs.py
cadenza_sdk/_resource.py
cadenza_sdk/_response.py
cadenza_sdk/_streaming.py
cadenza_sdk/_types.py
cadenza_sdk/_version.py
cadenza_sdk/pagination.py
cadenza_sdk/py.typed
cadenza_sdk/_utils/__init__.py
cadenza_sdk/_utils/_logs.py
cadenza_sdk/_utils/_proxy.py
cadenza_sdk/_utils/_reflection.py
cadenza_sdk/_utils/_streams.py
cadenza_sdk/_utils/_sync.py
cadenza_sdk/_utils/_transform.py
cadenza_sdk/_utils/_typing.py
cadenza_sdk/_utils/_utils.py
cadenza_sdk/lib/.keep
cadenza_sdk/resources/__init__.py
cadenza_sdk/resources/exchange_account.py
cadenza_sdk/resources/portfolio.py
cadenza_sdk/resources/utility.py
cadenza_sdk/resources/event/__init__.py
cadenza_sdk/resources/event/drop_copy.py
cadenza_sdk/resources/event/event.py
cadenza_sdk/resources/event/market_data.py
cadenza_sdk/resources/event/task.py
cadenza_sdk/resources/market/__init__.py
cadenza_sdk/resources/market/instrument.py
cadenza_sdk/resources/market/kline.py
cadenza_sdk/resources/market/market.py
cadenza_sdk/resources/market/orderbook.py
cadenza_sdk/resources/market/ticker.py
cadenza_sdk/resources/trading/__init__.py
cadenza_sdk/resources/trading/execution_report.py
cadenza_sdk/resources/trading/order.py
cadenza_sdk/resources/trading/quote.py
cadenza_sdk/resources/trading/trading.py
cadenza_sdk/resources/webhook/__init__.py
cadenza_sdk/resources/webhook/cloud_scheduler.py
cadenza_sdk/resources/webhook/webhook.py
cadenza_sdk/types/__init__.py
cadenza_sdk/types/balance_entry.py
cadenza_sdk/types/balance_entry_param.py
cadenza_sdk/types/event_new_params.py
cadenza_sdk/types/exchange_account.py
cadenza_sdk/types/exchange_account_balance.py
cadenza_sdk/types/exchange_account_create_params.py
cadenza_sdk/types/exchange_account_create_response.py
cadenza_sdk/types/exchange_account_credit.py
cadenza_sdk-0.23.1.dist-info/METADATA
cadenza_sdk-0.23.1.dist-info/WHEEL
cadenza_sdk-0.23.1.dist-info/licenses/LICENSE
cadenza_sdk-0.23.1.dist-info/RECORD
